{
    "header": "عبد الرحمن بن أبي عميرة المزني .",
    "id": "000387",
    "reference": "Šams al-dīn al-Ḏahabī (d. 748 AH). <i>Taʾrīḫ al-islām wa-wafayāt al-mašāhīr wa-al-aʿlām</i>. Ed. by ʿUmar Tadmurī. 2nd edition. 52 Vols. Bayrūt, 1990.",
    "source": "al-Ḏahabī’s <i>Taʾrīḫ al-islām</i>",
    "text": "<h1 class=\"arabic\">عبد الرحمن بن أبي عميرة المزني .\n</h1>\n<p class=\"arabic\">صحابي له أحاديث وقد سكن حمص وتاجر .\n</p>\n<p class=\"arabic\">روى عنه خالد بن معدان والقاسم أبو عبد الرحمن وربيعة بن يزيد القصير .\n</p>\n<p class=\"arabic\">وبعضهم يقول هو تابعي .\n\n</p>"
}