{
    "header": "عبد الله بن رباح أبو خالد الأنصاري المدنـ...",
    "id": "001077",
    "reference": "Šams al-dīn al-Ḏahabī (d. 748 AH). <i>Taʾrīḫ al-islām wa-wafayāt al-mašāhīr wa-al-aʿlām</i>. Ed. by ʿUmar Tadmurī. 2nd edition. 52 Vols. Bayrūt, 1990.",
    "source": "al-Ḏahabī’s <i>Taʾrīḫ al-islām</i>",
    "text": "<h1 class=\"arabic\">عبد الله بن رباح أبو خالد الأنصاري المدني نزيل البصرة .\n</h1>\n<p class=\"arabic\">روى عن أبي بن كعب وعمار بن ياسر وعمران بن حصين وكعب الأحبار .\n</p>\n<p class=\"arabic\">روى عنه ثابت البناني وأبو عمران الجوني وقتادة وخالد الحذاء .\n</p>\n<p class=\"arabic\">وهو ثقة جليل القدر .\n</p>\n<p class=\"arabic\">قال شعبة عن أبي عمران الجوني وقفت مع عبد الله بن رباح ونحن نقاتل الأزارقة \n  مع المهلب فبكى فقلت ما يبكيك فقال قد كان في قتال أهل الشرك غنى عن قتال \n  أهل القبلة .\n\n</p>"
}