{
    "header": "الحارث بن يعقوب الأنصاري م ت ن مولى قيس ...",
    "id": "002073",
    "reference": "Šams al-dīn al-Ḏahabī (d. 748 AH). <i>Taʾrīḫ al-islām wa-wafayāt al-mašāhīr wa-al-aʿlām</i>. Ed. by ʿUmar Tadmurī. 2nd edition. 52 Vols. Bayrūt, 1990.",
    "source": "al-Ḏahabī’s <i>Taʾrīḫ al-islām</i>",
    "text": "<h1 class=\"arabic\">الحارث بن يعقوب الأنصاري م ت ن مولى قيس بن سعد بن عبادة .\n</h1>\n<p class=\"arabic\">*8*71* مصري نبيل صالح كان يعد أفضل من ابنه عمرو بن الحارث .\n</p>\n<p class=\"arabic\">روى عن أبي الحباب سعيد بن يسار وعبد الرحمن بن شماسة وغير واحد وقيل إنه \n  روى عن سهل بن سعد .\n</p>\n<p class=\"arabic\">وعنه ابنه ويزيد بن أبي حبيب وهو أكبر منه والليث بن سعد وبكر ابن مضر وآخرون .\n</p>\n<p class=\"arabic\">روى يحيى بن بكير عن موسى بن ربيعة قال كان الحارث بن يعقوب من العباد إذا \n  انصرف من عشاء الآخرة دخل بيته فصلى ركعتين ويجاء بعشائه فيقول أصلي ركعتين \n  فلا يزال يصلي ركعتين ركعتين حتى يصبح فيكون عشاؤه وسجوده واحدا .\n</p>\n<p class=\"arabic\">وكان أبوه يعقوب من العباد أيضا .\n</p>\n<p class=\"arabic\">توفي الحارث في سنة ثلاثين ومائة .\n\n</p>"
}