{
    "header": "وساج بن عقبة بن وساج الأزدي .",
    "id": "006407",
    "reference": "Šams al-dīn al-Ḏahabī (d. 748 AH). <i>Taʾrīḫ al-islām wa-wafayāt al-mašāhīr wa-al-aʿlām</i>. Ed. by ʿUmar Tadmurī. 2nd edition. 52 Vols. Bayrūt, 1990.",
    "source": "al-Ḏahabī’s <i>Taʾrīḫ al-islām</i>",
    "text": "<h1 class=\"arabic\">وساج بن عقبة بن وساج الأزدي .\n</h1>\n<p class=\"arabic\">أبو عقبة المقدسي *14*426* .\n</p>\n<p class=\"arabic\">عن الهقل بن زياد وعبد الحميد بن أبي العشرين والوليد بن محمد الموقري .\n</p>\n<p class=\"arabic\">وعنه إبراهيم بن محمد الفريابي ثم المقدسي وسليمان بن عبد الحميد البهراني .\n</p>\n<p class=\"arabic\">ذكره ابن حبان في الثقات .\n\n</p>"
}