{
    "header": "زيد بن المبارك الصنعاني اليمني العابد .",
    "id": "006649",
    "reference": "Šams al-dīn al-Ḏahabī (d. 748 AH). <i>Taʾrīḫ al-islām wa-wafayāt al-mašāhīr wa-al-aʿlām</i>. Ed. by ʿUmar Tadmurī. 2nd edition. 52 Vols. Bayrūt, 1990.",
    "source": "al-Ḏahabī’s <i>Taʾrīḫ al-islām</i>",
    "text": "<h1 class=\"arabic\">زيد بن المبارك الصنعاني اليمني العابد .\n</h1>\n<p class=\"arabic\">*15*160* نزيل الرملة .\n</p>\n<p class=\"arabic\">عن رباح بن زيد ومحمد بن ثور وعبد الملك بن محمد ويوسف بن زكريا الصنعانيين \n  وسفيان بن عيينة .\n</p>\n<p class=\"arabic\">وعنه جعفر بن مسافر والرمادي وعباس بن عبد العظيم العنبري .\n</p>\n<p class=\"arabic\">وكان العنبري يعظمه ويثني عليه .\n</p>\n<p class=\"arabic\">وقال أبو حاتم صدوق قد أدركته .\n</p>\n<p class=\"arabic\">وقال عباس العنبري كنا نقول أحمد بن حنبل بالعراق وصدقة بن الفضل بخراسان \n  وزيد بن المبارك باليمن .\n\n</p>"
}