{
    "header": "سهل بن بكار خ د ن .",
    "id": "007187",
    "reference": "Šams al-dīn al-Ḏahabī (d. 748 AH). <i>Taʾrīḫ al-islām wa-wafayāt al-mašāhīr wa-al-aʿlām</i>. Ed. by ʿUmar Tadmurī. 2nd edition. 52 Vols. Bayrūt, 1990.",
    "source": "al-Ḏahabī’s <i>Taʾrīḫ al-islām</i>",
    "text": "<h1 class=\"arabic\">سهل بن بكار خ د ن .\n</h1>\n<p class=\"arabic\">*16*193* أبو بشر البصري .\n</p>\n<p class=\"arabic\">عن شعبة وجرير بن حازم ويزيد بن إبراهيم والسري بن يحيى وأبان بن يزيد وجويرية \n  بن أسماء وطائفة ) .\n</p>\n<p class=\"arabic\">وعنه خ ود وأبو زرعة وأبو حاتم ووثقه ومحمد بن محمد التمار وأبو مسلم الكجي \n  وآخرون .\n</p>\n<p class=\"arabic\">توفي سنة سبع أو ثمان وعشرين .\n</p>\n<p class=\"arabic\">وروى ن عن رجل عنه .\n\n</p>"
}