{
    "header": "هارون بن موسى بن حيان التميمي القزويني ....",
    "id": "008721",
    "reference": "Šams al-dīn al-Ḏahabī (d. 748 AH). <i>Taʾrīḫ al-islām wa-wafayāt al-mašāhīr wa-al-aʿlām</i>. Ed. by ʿUmar Tadmurī. 2nd edition. 52 Vols. Bayrūt, 1990.",
    "source": "al-Ḏahabī’s <i>Taʾrīḫ al-islām</i>",
    "text": "<h1 class=\"arabic\">هارون بن موسى بن حيان التميمي القزويني .\n</h1>\n<p class=\"arabic\">ق عن عبد الرحمن بن عبد الله الدشتكي وعبد العزيز بن المغيرة وإبراهيم بن \n  موسى الفراء وجماعة .\n</p>\n<p class=\"arabic\">وعنه ق وأبو زرعة وأبو حاتم وسعيد بن عمرو البرذعي وابنه موسى بن هارون .\n</p>\n<p class=\"arabic\">قال أبو حاتم ثقة صدوق .\n</p>\n<p class=\"arabic\">وقال أبو يعلى الخليلي ثقة كبير المحل مشهور بالديانة والعلم والإمامة .\n</p>\n<p class=\"arabic\">مات في سنة ثمان وأربعين ومائتين .\n\n</p>"
}