{
    "header": "أحمد بن محمد بن أنس .",
    "id": "008889",
    "reference": "Šams al-dīn al-Ḏahabī (d. 748 AH). <i>Taʾrīḫ al-islām wa-wafayāt al-mašāhīr wa-al-aʿlām</i>. Ed. by ʿUmar Tadmurī. 2nd edition. 52 Vols. Bayrūt, 1990.",
    "source": "al-Ḏahabī’s <i>Taʾrīḫ al-islām</i>",
    "text": "<h1 class=\"arabic\">أحمد بن محمد بن أنس .\n</h1>\n<p class=\"arabic\">أبو العباس بن القربيطي البغدادي الحافظ .\n</p>\n<p class=\"arabic\">عن إبراهيم بن زياد سبلان وأبي حفص الفلاس .\n</p>\n<p class=\"arabic\">وعنه أبو حاتم الرازي ومحمد بن سعد وهما أكبر منه ومحمد بن مخلد وعبد الرحمن \n  بن أبي حاتم .\n</p>\n<p class=\"arabic\">له ذكر في السابق واللاحق .\n</p>\n<p class=\"arabic\">بقي إلى حدود الستين ومائتين .\n\n</p>"
}