{
    "header": "بشر بن عبد الوهاب .",
    "id": "008970",
    "reference": "Šams al-dīn al-Ḏahabī (d. 748 AH). <i>Taʾrīḫ al-islām wa-wafayāt al-mašāhīr wa-al-aʿlām</i>. Ed. by ʿUmar Tadmurī. 2nd edition. 52 Vols. Bayrūt, 1990.",
    "source": "al-Ḏahabī’s <i>Taʾrīḫ al-islām</i>",
    "text": "<h1 class=\"arabic\">بشر بن عبد الوهاب .\n</h1>\n<p class=\"arabic\">أبو الحسن الدمشقي مولى بني أمية ويقال له بشير .\n</p>\n<p class=\"arabic\">شيخ زاهد جليل .\n</p>\n<p class=\"arabic\">روى عن الوليد بن مسلم ووكيع ومروان بن معاوية وضمرة *19*93* ومحمد بن شعيب \n  ومحمد بن بشر العبدي .\n</p>\n<p class=\"arabic\">وعنه ابنه أحمد ومحمد بن الفيض الغساني وأبو بشر الدولابي وابن جوصا وطائفة .\n</p>\n<p class=\"arabic\">توفي في رجب سنة أربع وخمسين .\n</p>\n<p class=\"arabic\">لم يضعفه أحد فهو حسن الحديث وهو الذي تفرد عن وكيع بمسلسل العيدين رواه عنه \n  أحمد بن محمد ابن أخت سليمان بن حرب وأحمد بن عبيد الله الفراسي وقيل بل هذا \n  الفراسي هو ابن أخت سليمان وكنيته أبو عبيد الله وهذا الصحيح من اسمه أنه \n  أحمد بن محمد بن فراس بن الهيثم وتفرد بالحديث .\n\n</p>"
}