{
    "header": "يوسف بن واضح البصري المؤدب .",
    "id": "009440",
    "reference": "Šams al-dīn al-Ḏahabī (d. 748 AH). <i>Taʾrīḫ al-islām wa-wafayāt al-mašāhīr wa-al-aʿlām</i>. Ed. by ʿUmar Tadmurī. 2nd edition. 52 Vols. Bayrūt, 1990.",
    "source": "al-Ḏahabī’s <i>Taʾrīḫ al-islām</i>",
    "text": "<h1 class=\"arabic\">يوسف بن واضح البصري المؤدب .\n</h1>\n<p class=\"arabic\">ن روى عن قدامة بن شهاب ومعتمر بن سليمان وغيرهما .\n</p>\n<p class=\"arabic\">وعنه ن ثم روى عن رجل عنه وعبد الله بن ناجية وإمام الأئمة ابن خزيمة وآخرون .\n</p>\n<p class=\"arabic\">مات سنة إحدى وخمسين .\n\n</p>"
}