{
    "header": "إبراهيم بن محمد بن عبد الله بن المدبر .",
    "id": "009870",
    "reference": "Šams al-dīn al-Ḏahabī (d. 748 AH). <i>Taʾrīḫ al-islām wa-wafayāt al-mašāhīr wa-al-aʿlām</i>. Ed. by ʿUmar Tadmurī. 2nd edition. 52 Vols. Bayrūt, 1990.",
    "source": "al-Ḏahabī’s <i>Taʾrīḫ al-islām</i>",
    "text": "<h1 class=\"arabic\">إبراهيم بن محمد بن عبد الله بن المدبر .\n</h1>\n<p class=\"arabic\">الوزير أبو إسحاق الضبي الكاتب الأديب الشاعر .\n</p>\n<p class=\"arabic\">ولي الوزارة مرة للمعتمد .\n</p>\n<p class=\"arabic\">وتفي سنة تسع وسبعين وكان أحد من جمع بين الرياسة والأدب والبلاغة وهو أخو \n  أحمد ومحمد *20*295* .\n</p>\n<p class=\"arabic\">حكى عنه علي بن سليمان الأخفش وجحعفر بن قدامة ومحمد بن يحيى الصولي وقال \n  كان جليلا عالما ليس في الكتاب من يدانيه في علمه وكتابته .\n</p>\n<p class=\"arabic\">ولم يزل في رتبة الوزير حضر في سنة ثلاث وستين للوزارة فاستعفى لعظم المطالبة \n  بالمال .\n</p>\n<p class=\"arabic\">وفيه يقول أبو هفان .\n</p>\n<p class=\"arabic\">% أيا ابن المدبر أنت علمت الورى % % بذل النوال وهم به بخلاء % .\n</p>\n<p class=\"arabic\">% لو كان مثلك في البرية واحد % % في الجود لم يك فيهم فقراء % .\n</p>\n<p class=\"arabic\">عاش الوزير المدبر تسعا وتسعين سنة .\n</p>\n<p class=\"arabic\">ساق ترجمته ابن النجار في تسع ورقات .\n\n</p>"
}