{
    "header": "رجاء بن عبد الله الهروي الوراق .",
    "id": "009967",
    "reference": "Šams al-dīn al-Ḏahabī (d. 748 AH). <i>Taʾrīḫ al-islām wa-wafayāt al-mašāhīr wa-al-aʿlām</i>. Ed. by ʿUmar Tadmurī. 2nd edition. 52 Vols. Bayrūt, 1990.",
    "source": "al-Ḏahabī’s <i>Taʾrīḫ al-islām</i>",
    "text": "<h1 class=\"arabic\">رجاء بن عبد الله الهروي الوراق .\n</h1>\n<p class=\"arabic\">كان عنده مصنفات مالك بن سليمان الهروي ومصنفات سعيد بن منصور ) .\n</p>\n<p class=\"arabic\">وروى أيضا عن أحمد بن يونس ومهدي بن جعفر الملي وجماعة .\n</p>\n<p class=\"arabic\">وكان من أعيان المحدثين بهراة .\n</p>\n<p class=\"arabic\">روى عنه الحافظان أبو إسحاق البزاز وأبو الفضل بن إسحاق .\n</p>\n<p class=\"arabic\">توفي سنة بع وسبعين وقيل سنة تسع وسبعين ومائتين .\n\n</p>"
}