{
    "header": "عبد الله بن محمد بن سلام .",
    "id": "010681",
    "reference": "Šams al-dīn al-Ḏahabī (d. 748 AH). <i>Taʾrīḫ al-islām wa-wafayāt al-mašāhīr wa-al-aʿlām</i>. Ed. by ʿUmar Tadmurī. 2nd edition. 52 Vols. Bayrūt, 1990.",
    "source": "al-Ḏahabī’s <i>Taʾrīḫ al-islām</i>",
    "text": "<h1 class=\"arabic\">عبد الله بن محمد بن سلام .\n</h1>\n<p class=\"arabic\">أبو بكر الإصبهاني .\n</p>\n<p class=\"arabic\">عن أبي توبة بن نافع الحلبي ومحمد بن سعيد بن سابق .\n</p>\n<p class=\"arabic\">وعنه أبو علي الصحاف والإصبهانيون .\n</p>\n<p class=\"arabic\">توفي سنة إحدى أيضا .\n</p>\n<p class=\"arabic\">ومن الرواة عنه أبو بكر القباب وأحمد بن جعفر بن مفيد .\n</p>\n<p class=\"arabic\">فيه ضعف .\n\n</p>"
}