{
    "header": "أحمد بن يحيى بن الإمام يحيى بن يحيى الليـ...",
    "id": "011142",
    "reference": "Šams al-dīn al-Ḏahabī (d. 748 AH). <i>Taʾrīḫ al-islām wa-wafayāt al-mašāhīr wa-al-aʿlām</i>. Ed. by ʿUmar Tadmurī. 2nd edition. 52 Vols. Bayrūt, 1990.",
    "source": "al-Ḏahabī’s <i>Taʾrīḫ al-islām</i>",
    "text": "<h1 class=\"arabic\">أحمد بن يحيى بن الإمام يحيى بن يحيى الليثي الأندلسي .\n</h1>\n<p class=\"arabic\">*22*89* المعروف بالثائر فقيه بارع وشاعر محسن .\n</p>\n<p class=\"arabic\">توفي كهلا وقد روى عن أبيه ومحمد بن وضاح .\n</p>\n<p class=\"arabic\">ومات سنة سبع وتسعين .\n\n</p>"
}