{
    "header": "عبد الحكم بن محمد بن سلام .",
    "id": "012840",
    "reference": "Šams al-dīn al-Ḏahabī (d. 748 AH). <i>Taʾrīḫ al-islām wa-wafayāt al-mašāhīr wa-al-aʿlām</i>. Ed. by ʿUmar Tadmurī. 2nd edition. 52 Vols. Bayrūt, 1990.",
    "source": "al-Ḏahabī’s <i>Taʾrīḫ al-islām</i>",
    "text": "<h1 class=\"arabic\">عبد الحكم بن محمد بن سلام .\n</h1>\n<p class=\"arabic\">أبو عثمان الصدفي مولاهم المصري .\n</p>\n<p class=\"arabic\">روى عن عيسى زغبة وأبي الطاهر بن السرح وذي النون المصري وغيرهم .\n</p>\n<p class=\"arabic\">قال ابن يونس كان صدوقا ألا إنه إنقطع من أوائل أصوله شيء ولم يكن ممن يميز \n  فحدث بما لم يسمع فثبتناه ورجع وكان كثير الحديث .\n</p>\n<p class=\"arabic\">قال لي ولدت سنة تسع وعشرين ومائتين .\n</p>\n<p class=\"arabic\">قلت روى عنه ابن يونس وأبو بكر بن المقري وجماعة .\n\n</p>"
}