{
    "header": "إسماعيل بن العباس بن عمر بن مهران .",
    "id": "013353",
    "reference": "Šams al-dīn al-Ḏahabī (d. 748 AH). <i>Taʾrīḫ al-islām wa-wafayāt al-mašāhīr wa-al-aʿlām</i>. Ed. by ʿUmar Tadmurī. 2nd edition. 52 Vols. Bayrūt, 1990.",
    "source": "al-Ḏahabī’s <i>Taʾrīḫ al-islām</i>",
    "text": "<h1 class=\"arabic\">إسماعيل بن العباس بن عمر بن مهران .\n</h1>\n<p class=\"arabic\">أبو علي الوراق .\n</p>\n<p class=\"arabic\">ولد سنة أربعين ومائتين وسمع الحسن بن عرفة والزبير بن بكار وعلي بن حرب وطائفة .\n</p>\n<p class=\"arabic\">وعنه ابنه محمد والدار قطني والمخلص وعيسى بن الوزير .\n</p>\n<p class=\"arabic\">ووثقه الدار قطني .\n</p>\n<p class=\"arabic\">مات في المحرم راجعا من الحج .\n</p>\n<p class=\"arabic\">قرأت على الأبرقوهي أنا الفتح أنا هبة الله أنا ابن النقور ثنا عيسى أنا إسماعيل \n  الوراق اثنا الحسن بن عرفة حدثني المحاربي عن محمد عن عمرو عن أ بي سلمة عن \n  أبي هريرة عن النبي صلى الله عليه وسلم قال أعمار أمتي ما بين الستين إلى \n  السبعين وأقلهم من يجوز ذلك .\n</p>\n<p class=\"arabic\">هذا حديث حسن عال .\n\n</p>"
}