{
    "header": "أحمد بن محمد بن محمد بن سليمان بن الحارثـ...",
    "id": "013506",
    "reference": "Šams al-dīn al-Ḏahabī (d. 748 AH). <i>Taʾrīḫ al-islām wa-wafayāt al-mašāhīr wa-al-aʿlām</i>. Ed. by ʿUmar Tadmurī. 2nd edition. 52 Vols. Bayrūt, 1990.",
    "source": "al-Ḏahabī’s <i>Taʾrīḫ al-islām</i>",
    "text": "<h1 class=\"arabic\">أحمد بن محمد بن محمد بن سليمان بن الحارث .\n</h1>\n<p class=\"arabic\">أبو ذر الباغندي واسطي الأصل البغدادي الدار .\n</p>\n<p class=\"arabic\">سمع عمر بن شبة وعبيد الله بن سعد الأزهري وعلي بن إشكاب وسعدان بن نصر .\n</p>\n<p class=\"arabic\">وعنه الدارقطني والمعافى وأبو حفص بن شاهين *24*188* .\n</p>\n<p class=\"arabic\">قال فيه الدارقطني ما علمت إلا خيرا وأصحابنا يؤثرونه على أبيه .\n\n</p>"
}