{
    "header": "القاسم بن أحمد بن إبراهيم بن محمد بن عبيـ...",
    "id": "015489",
    "reference": "Šams al-dīn al-Ḏahabī (d. 748 AH). <i>Taʾrīḫ al-islām wa-wafayāt al-mašāhīr wa-al-aʿlām</i>. Ed. by ʿUmar Tadmurī. 2nd edition. 52 Vols. Bayrūt, 1990.",
    "source": "al-Ḏahabī’s <i>Taʾrīḫ al-islām</i>",
    "text": "<h1 class=\"arabic\">القاسم بن أحمد بن إبراهيم بن محمد بن عبيد الله بن موسى بن جعفر  \n  الصادق بن محمد البقر بن زين العابدين أبو محمد الحسيني رحمه الله تعالى .\n</h1>\n<p class=\"arabic\">توفي في رمضان وله أربع وثمانون سنة .\n\n</p>"
}