{
    "header": "أحمد بن خالد بن عبد الله بن يبقى الجذاميـ...",
    "id": "016131",
    "reference": "Šams al-dīn al-Ḏahabī (d. 748 AH). <i>Taʾrīḫ al-islām wa-wafayāt al-mašāhīr wa-al-aʿlām</i>. Ed. by ʿUmar Tadmurī. 2nd edition. 52 Vols. Bayrūt, 1990.",
    "source": "al-Ḏahabī’s <i>Taʾrīḫ al-islām</i>",
    "text": "<h1 class=\"arabic\">أحمد بن خالد بن عبد الله بن يبقى الجذامي القرطبي أبو عمر التاجر .\n</h1>\n<p class=\"arabic\">رحل وسمع من أبي علي الصفار والحسين بن صفوان وأبي البختري وأبي سعيد بن الأعرابي .\n</p>\n<p class=\"arabic\">وأدخل الأندلس أشياء تفرد بروايتها فسمع الناس منه ولم يكن له فهم ولا كان \n  يقيم الهجاء غير أنه كان صالحا صدوقا إن شاء الله سمعت منه أكثر ما يرويه \n  قاله ابن الفرضي .\n</p>\n<p class=\"arabic\">توفي في ذي القعدة .\n\n</p>"
}