{
    "header": "طلخة بن عمر الحذاء بغدادي .",
    "id": "016273",
    "reference": "Šams al-dīn al-Ḏahabī (d. 748 AH). <i>Taʾrīḫ al-islām wa-wafayāt al-mašāhīr wa-al-aʿlām</i>. Ed. by ʿUmar Tadmurī. 2nd edition. 52 Vols. Bayrūt, 1990.",
    "source": "al-Ḏahabī’s <i>Taʾrīḫ al-islām</i>",
    "text": "<h1 class=\"arabic\">طلخة بن عمر الحذاء بغدادي .\n</h1>\n<p class=\"arabic\">يروي عن الباغندي وأبي القاسم البغوي .\n</p>\n<p class=\"arabic\">وعنه بشرى الفاتني وعبد العزيز الأزجي *26*673* .\n\n</p>"
}