{
    "header": "سعيد بن أحمد بن سعيد بن موسى بن جدير .",
    "id": "016837",
    "reference": "Šams al-dīn al-Ḏahabī (d. 748 AH). <i>Taʾrīḫ al-islām wa-wafayāt al-mašāhīr wa-al-aʿlām</i>. Ed. by ʿUmar Tadmurī. 2nd edition. 52 Vols. Bayrūt, 1990.",
    "source": "al-Ḏahabī’s <i>Taʾrīḫ al-islām</i>",
    "text": "<h1 class=\"arabic\">سعيد بن أحمد بن سعيد بن موسى بن جدير .\n</h1>\n<p class=\"arabic\">أبو عثمان *27*255* القرطبي صالح زاهد متقشف سمع خالد بن سعد وأحمد بن سعيد \n  بن حزم وأحمد بن مسور وجماعة .\n</p>\n<p class=\"arabic\">روى عنه ابن الفرضي .\n\n</p>"
}