{
    "header": "محمد بن علي بن عبد العزيز بن إبراهيم .",
    "id": "018897",
    "reference": "Šams al-dīn al-Ḏahabī (d. 748 AH). <i>Taʾrīḫ al-islām wa-wafayāt al-mašāhīr wa-al-aʿlām</i>. Ed. by ʿUmar Tadmurī. 2nd edition. 52 Vols. Bayrūt, 1990.",
    "source": "al-Ḏahabī’s <i>Taʾrīḫ al-islām</i>",
    "text": "<h1 class=\"arabic\">محمد بن علي بن عبد العزيز بن إبراهيم .\n</h1>\n<p class=\"arabic\">أبو الفضل الكاتب البغدادي المعروف بابن حاجب النعمان .\n</p>\n<p class=\"arabic\">كان أبوه وزيرا للقادر بالله فلما مات أبوه وزر هو للقادر في سنة إحدى وعشرين \n  ثم عزل بعد ستة أشهر فلما استخلف القائم استوزره وكان أديبا شاعرا كاتبا توفي \n  في ثامن ذي القعدة وله سبعون سنة وقد فلج قبل موته مدة أعوام وله في الشمعة .\n</p>\n<p class=\"arabic\">% وطفلة كالرمح لا حظتها % % سنانها من ذهب قد طبع % .\n</p>\n<p class=\"arabic\">% دموعها تنهل في نحرها % % ورأسها يحيى إذا ما قطع % .\n\n</p>"
}