{
    "header": "إسماعيل بن خف بن سعيد بن عمران .",
    "id": "019750",
    "reference": "Šams al-dīn al-Ḏahabī (d. 748 AH). <i>Taʾrīḫ al-islām wa-wafayāt al-mašāhīr wa-al-aʿlām</i>. Ed. by ʿUmar Tadmurī. 2nd edition. 52 Vols. Bayrūt, 1990.",
    "source": "al-Ḏahabī’s <i>Taʾrīḫ al-islām</i>",
    "text": "<h1 class=\"arabic\">إسماعيل بن خف بن سعيد بن عمران .\n</h1>\n<p class=\"arabic\">*30*377* أبو الطاهر الأنصاري الأندلسي المقريء .\n</p>\n<p class=\"arabic\">مصنف العنوان في القراءات .\n</p>\n<p class=\"arabic\">قرأ على عبد الجبار بن أحمد الطرسوسي بمصر وسكنها وتصدر للإقراء .\n</p>\n<p class=\"arabic\">أخذ عنه جماهر بن عبد الرحمن الفقيه وأبو الحسين الخشاب وابنه جعفر بن إسماعيل \n  بن خلف .\n</p>\n<p class=\"arabic\">وكان مع براعته في القراءات إماما في النحو اختصر كتاب الحجة لأبي علي الفارسي \n  ) .\n</p>\n<p class=\"arabic\">وتوفي مستهل المحرم .\n\n</p>"
}