{
    "header": "محمد بن أحمد بن أبي عمر المظهر بن أبي نزـ...",
    "id": "022454",
    "reference": "Šams al-dīn al-Ḏahabī (d. 748 AH). <i>Taʾrīḫ al-islām wa-wafayāt al-mašāhīr wa-al-aʿlām</i>. Ed. by ʿUmar Tadmurī. 2nd edition. 52 Vols. Bayrūt, 1990.",
    "source": "al-Ḏahabī’s <i>Taʾrīḫ al-islām</i>",
    "text": "<h1 class=\"arabic\">محمد بن أحمد بن أبي عمر المظهر بن أبي نزار محمد بن علي بن محمد بن أحمد \n  بن بجير .\n</h1>\n<p class=\"arabic\">*35*404* .\n</p>\n<p class=\"arabic\">الرئيس أبو عدنان الربعي الإصبهاني .\n</p>\n<p class=\"arabic\">من أولاد المحدثين .\n</p>\n<p class=\"arabic\">ولد سنة أربع وثلاثين وأربعمائة .\n</p>\n<p class=\"arabic\">وسمع المعجم الصغير من ابن ريذة .\n</p>\n<p class=\"arabic\">ورى عنه يحيى الثقفي وأبو موسى وقال توفي في ربيع الأول .\n</p>\n<p class=\"arabic\">وأجاز للسمعاني وقال فيه شيخ سديد صالح وهو والد شيخنا عبد المغيث وعبد الجليل .\n</p>\n<p class=\"arabic\">وسمع من جده المطهر وجعفر بن محمد بن جعفر وأبي القاسم عبد الرحمن بن محمد \n  الذكواني .\n</p>\n<p class=\"arabic\">يروي كتاب الرهان للأسلمي عن الذكواني عن أبى عثمان عن الشعراني عنه وكتاب \n  معرفة شيوخ شعبة ألفه أبو داود الطيالسي بسماعه من الذكواني عن أبي الشيخ \n  وكتاب العيد لأبي الشيخ وألطعمة لابن أبي عاصم والسنة ليعقوب الفسوي المحنة \n  جمع صالح بن أحمد وعدة تواليف ذكرها السمعاني .\n\n</p>"
}