{
    "header": "محمود بن محمد بن الحسين .",
    "id": "026334",
    "reference": "Šams al-dīn al-Ḏahabī (d. 748 AH). <i>Taʾrīḫ al-islām wa-wafayāt al-mašāhīr wa-al-aʿlām</i>. Ed. by ʿUmar Tadmurī. 2nd edition. 52 Vols. Bayrūt, 1990.",
    "source": "al-Ḏahabī’s <i>Taʾrīḫ al-islām</i>",
    "text": "<h1 class=\"arabic\">محمود بن محمد بن الحسين .\n</h1>\n<p class=\"arabic\">الفقيه أبو القاسم القزويني الشافعي الواعظ .\n</p>\n<p class=\"arabic\">ولد سنة سبع وعشرين وخمسمائة وحدث بمصر عن أبي شجاع عمر بن محمد البسطتمي \n  وأبي القاسم بن عساكر واللفي .\n</p>\n<p class=\"arabic\">ودرس بمشهد الحسين مدة ووعظ .\n</p>\n<p class=\"arabic\">وتوفي في صفر .\n\n</p>"
}