{
    "header": "عبيد الله بن محمد بن عبد الجليل بن محمد ...",
    "id": "026909",
    "reference": "Šams al-dīn al-Ḏahabī (d. 748 AH). <i>Taʾrīḫ al-islām wa-wafayāt al-mašāhīr wa-al-aʿlām</i>. Ed. by ʿUmar Tadmurī. 2nd edition. 52 Vols. Bayrūt, 1990.",
    "source": "al-Ḏahabī’s <i>Taʾrīḫ al-islām</i>",
    "text": "<h1 class=\"arabic\">عبيد الله بن محمد بن عبد الجليل بن محمد .\n</h1>\n<p class=\"arabic\">القاضي أبو محمد بن الشيخ أبي الفتح الساوي ثم البغدادي الفقيه الحنفي أحد \n  العدول والأكابر .\n</p>\n<p class=\"arabic\">ناب في الحكم بدار الخلافة ثم بمدينة السلام بغداد وكان محمود السيرة .\n</p>\n<p class=\"arabic\">ولد سنة ثلاث عشرة وخمسمائة في أولها .\n</p>\n<p class=\"arabic\">وسمع من أبن الحصين وابن الطبر وأبي الحسين بن الفراء وجماعة .\n</p>\n<p class=\"arabic\">وكان آخر من بقي من بيت الساوي ولم يعقب .\n</p>\n<p class=\"arabic\">روى عنه الدبيثي وابن خليل والبغاددة .\n</p>\n<p class=\"arabic\">وتوفي في تاسع المحرم .\n\n</p>"
}