{
    "header": "محمد بن غنيمة بن علي .",
    "id": "027126",
    "reference": "Šams al-dīn al-Ḏahabī (d. 748 AH). <i>Taʾrīḫ al-islām wa-wafayāt al-mašāhīr wa-al-aʿlām</i>. Ed. by ʿUmar Tadmurī. 2nd edition. 52 Vols. Bayrūt, 1990.",
    "source": "al-Ḏahabī’s <i>Taʾrīḫ al-islām</i>",
    "text": "<h1 class=\"arabic\">محمد بن غنيمة بن علي .\n</h1>\n<p class=\"arabic\">أبو عبد الله الحريمي القزاز المعروف بابن القاق وهو فلقبه عصفور .\n</p>\n<p class=\"arabic\">شيخ معمر قارب المائة وسمع في شبيبة من أبي الحسين محمد بن أبي يعلى الفراء .\n</p>\n<p class=\"arabic\">روى عنه الدبيثي .\n</p>\n<p class=\"arabic\">وبالإجازة ابن أبي الخير .\n</p>\n<p class=\"arabic\">توفي في رابع شعبان .\n</p>\n<p class=\"arabic\">وروى عنه ابن النجار ووصفه بالصلاح ) .\n\n</p>"
}