{
    "header": "الحافظة اسمها أرغوان .",
    "id": "030922",
    "reference": "Šams al-dīn al-Ḏahabī (d. 748 AH). <i>Taʾrīḫ al-islām wa-wafayāt al-mašāhīr wa-al-aʿlām</i>. Ed. by ʿUmar Tadmurī. 2nd edition. 52 Vols. Bayrūt, 1990.",
    "source": "al-Ḏahabī’s <i>Taʾrīḫ al-islām</i>",
    "text": "<h1 class=\"arabic\">الحافظة اسمها أرغوان .\n</h1>\n<p class=\"arabic\">عتيقة الملك العادل وهي التي ربت الملك الحافظ صاحب قلعة جعبر .\n</p>\n<p class=\"arabic\">كانت بدمشق وكانت تبعث إلى القلعة بالأطعمة والثياب إلى الملك المغيث عمر \n  بن الملك الصالح نجم الدين أيوب وهو محبوس فحقد عليها الصالح إسماعيل وصادرها \n  وأخذ منها أموالا كثيرة .\n</p>\n<p class=\"arabic\">بنت لها تربة مليحة فوق عين الكرش ووقفت دارها بدمشق على خدامها وعاشت زمانا .\n\n</p>"
}