{
    "header": " علي بن محمد بن الرضا بن حمزة بن أميركا ...",
    "id": "031443",
    "reference": "Šams al-dīn al-Ḏahabī (d. 748 AH). <i>Taʾrīḫ al-islām wa-wafayāt al-mašāhīr wa-al-aʿlām</i>. Ed. by ʿUmar Tadmurī. 2nd edition. 52 Vols. Bayrūt, 1990.",
    "source": "al-Ḏahabī’s <i>Taʾrīḫ al-islām</i>",
    "text": "<h1 class=\"arabic\"> علي بن محمد بن الرضا بن حمزة بن أميركا .\n</h1>\n<p class=\"arabic\">الشريف أبو الحسن الحسيني الموسوي الطوسي الأديب الشاعر المعروف بابن دفتر \n  خوان .\n</p>\n<p class=\"arabic\">ولد بحماه وبها توفي في ربيع الآخر وله ست وستون سنة .\n</p>\n<p class=\"arabic\">كان فاضلا شاعرا محسنا له مصنفات أدبية وقد امتدح المستنصر بالله وغيره .\n\n</p>"
}