{
    "header": " محمد بن يوسف بن محمد  .",
    "id": "031704",
    "reference": "Šams al-dīn al-Ḏahabī (d. 748 AH). <i>Taʾrīḫ al-islām wa-wafayāt al-mašāhīr wa-al-aʿlām</i>. Ed. by ʿUmar Tadmurī. 2nd edition. 52 Vols. Bayrūt, 1990.",
    "source": "al-Ḏahabī’s <i>Taʾrīḫ al-islām</i>",
    "text": "<h1 class=\"arabic\"> محمد بن يوسف بن محمد  .\n</h1>\n<p class=\"arabic\">الفخر الكنجي نزيل دمشق .\n</p>\n<p class=\"arabic\">عني بالحديث وسمع الكثير ورحل وحصل ثم إنه بدا منه فضول في أيام التتار بدمشق .\n</p>\n<p class=\"arabic\">قال الإمام أبو شامة قتل بجامع دمشق يوم التاسع والعشرين من رمضان وكان فقيها \n  محدثا لكنه كان كثير الكلام يميل إلى الرفض جمع كتبا في التشيع وداخل التتار \n  فانتدب له من تأذى منه فبقر بطنه بالجامع .\n</p>\n<p class=\"arabic\">قتل كما قتل غيره من أعوان التتار مثل الشمس محمد بن عباس الماكسيني وابن \n  البغيل الذي كان يسخر الدواب .\n\n</p>"
}