{
    "header": " إبراهيم بن إسحاق بن المظفر .",
    "id": "033409",
    "reference": "Šams al-dīn al-Ḏahabī (d. 748 AH). <i>Taʾrīḫ al-islām wa-wafayāt al-mašāhīr wa-al-aʿlām</i>. Ed. by ʿUmar Tadmurī. 2nd edition. 52 Vols. Bayrūt, 1990.",
    "source": "al-Ḏahabī’s <i>Taʾrīḫ al-islām</i>",
    "text": "<h1 class=\"arabic\"> إبراهيم بن إسحاق بن المظفر .\n</h1>\n<p class=\"arabic\">الشيخ برهان الدين أبو إسحاق المصري الوزيري المقرئ من حارة الوزيرية بالقاهرة \n  ولد سنة تسع عشرة وستمائة وحفظ العنوان وقرأ بها أعني القراءآت على التقي \n  عبد القوي بن المغربل صاحب أبي الجود سنة أربعين وقرأ بعدة كتب على الكمال \n  الضرير وراح إلى الصعيد فقرأ على محمد بن محمد بن الفصال وقرأ بدمشق على علم \n  الدين القاسم وعلى الكمال بن فارس .\n</p>\n<p class=\"arabic\">وعني بالقراءآت وأقرأ بها وسمع الحديث وأسمع ابنه إسحاق .\n\n</p>"
}