{
    "header": " النجم بن عساكر .",
    "id": "034999",
    "reference": "Šams al-dīn al-Ḏahabī (d. 748 AH). <i>Taʾrīḫ al-islām wa-wafayāt al-mašāhīr wa-al-aʿlām</i>. Ed. by ʿUmar Tadmurī. 2nd edition. 52 Vols. Bayrūt, 1990.",
    "source": "al-Ḏahabī’s <i>Taʾrīḫ al-islām</i>",
    "text": "<h1 class=\"arabic\"> النجم بن عساكر .\n</h1>\n<p class=\"arabic\">هو محمد بن إبراهيم بن محمود بن تاج الأمناء ابن عم بهاء الدين القاسم بن \n  مظفر الطبيب وهو عم الإمام شرف الدين حسين بن سلام لأمه .\n</p>\n<p class=\"arabic\">كان فيه زهد وانجماع وانقباض فيه دين ومعرفة .\n</p>\n<p class=\"arabic\">توفي كهلا في ذي الحجة وله سماعات ولم يحدث .\n\n</p>"
}